triplets/__init__.py
triplets/_version.py
triplets/cgmes_tools.py
triplets/rdf_parser.py
triplets/export_schema/ENTSO-E_Object Registry vocabulary_2.1.1_2022-12-29.json
triplets/export_schema/ENTSOE_CGMES_2.4.15_552_ED1.json
triplets/export_schema/ENTSOE_CGMES_2.4.15_552_ED2.json
triplets/export_schema/ENTSOE_CGMES_3.0.0_552_ED1.json
triplets/export_schema/ENTSOE_CGMES_3.0.0_552_ED2.json
triplets/export_schema/ENTSOE_NC_552_ED1.json
triplets/export_schema/ENTSOE_NC_552_ED2.json
triplets/export_schema/__init__.py
triplets/rdfs_tools/RDFS_to_AzureDTDL_V2.py
triplets/rdfs_tools/__init__.py
triplets/rdfs_tools/cim_rdfs_to_html.py
triplets/rdfs_tools/cim_rdfs_to_json.py
triplets/rdfs_tools/cim_rdfs_to_json_deprecated.py
triplets/rdfs_tools/rdfs_tools.py
triplets-0.0.17.dist-info/METADATA
triplets-0.0.17.dist-info/WHEEL
triplets-0.0.17.dist-info/top_level.txt
triplets-0.0.17.dist-info/RECORD
