Metadata-Version: 2.4
Name: triplets
Version: 0.0.17
Summary: Simple tools to load/modify/export XML/RDF data using Pandas DataFrames
Home-page: https://github.com/Haigutus/triplets
Author: Kristjan Vilgo
Author-email: kristjan.vilgo@gmail.com
License: MIT
Classifier: Programming Language :: Python :: 3
Classifier: License :: OSI Approved :: MIT License
Classifier: Operating System :: OS Independent
Requires-Dist: pandas
Requires-Dist: lxml
Requires-Dist: aniso8601
Dynamic: author
Dynamic: author-email
Dynamic: classifier
Dynamic: description
Dynamic: description-content-type
Dynamic: home-page
Dynamic: license
Dynamic: requires-dist
Dynamic: summary
